fftfilter/__init__.py
fftfilter/fftfilter.py
fftfilter-0.3.dist-info/licenses/LICENSE
fftfilter-0.3.dist-info/METADATA
fftfilter-0.3.dist-info/WHEEL
fftfilter-0.3.dist-info/entry_points.txt
fftfilter-0.3.dist-info/top_level.txt
fftfilter-0.3.dist-info/RECORD
